{
  "system": {
    "name": "HMRC Call Automation System",
    "version": "1.0.0",
    "description": "Automated HMRC calling system to save team time"
  },
  "ucm6308": {
    "host": "192.168.1.148",
    "port": 8089,
    "user": "Brigain",
    "password": "Jen!fer1",
    "https": true
  },
  "hmrc": {
    "primaryNumber": "0300 200 3000",
    "testNumber": "07977252412",
    "timeoutSeconds": 300,
    "maxRetries": 3
  },
  "team": {
    "defaultExtension": "1001",
    "availableExtensions": ["1001", "1002", "1003"]
  },
  "elevenlabs": {
    "apiKey": "sk_339789244131452085271147222357754574120707517174114414303103025",
    "voiceId": "21m00Tcm4TlvDq8ikWAM",
    "model": "eleven_turbo_v2"
  },
  "database": {
    "googleSheets": {
      "spreadsheetId": "1v-1SkHzSMdpHyxMqQluDo7_--sj69cUH9SXCtuqLENQ",
      "sheetId": 1897655295
    }
  }
}